VisioNomicon/__init__.py
VisioNomicon/args_handler.py
VisioNomicon/constants.py
VisioNomicon/gpt.py
VisioNomicon/main.py
VisioNomicon-0.1.7.dist-info/LICENSE
VisioNomicon-0.1.7.dist-info/METADATA
VisioNomicon-0.1.7.dist-info/WHEEL
VisioNomicon-0.1.7.dist-info/entry_points.txt
VisioNomicon-0.1.7.dist-info/top_level.txt
VisioNomicon-0.1.7.dist-info/RECORD
