Metadata-Version: 2.1
Name: VisioNomicon
Version: 0.1.7
Summary: A utility leveraging GPT-4o for image file renaming based on content.
Home-page: https://github.com/rehanzo/visionomicon
Author: Rehan Rana
Author-email: visionomicon@rehanzo.com
Keywords: gpt-4 gpt-4v gpt-4o openai renaming images
Classifier: Programming Language :: Python :: 3
Classifier: License :: OSI Approved :: GNU General Public License v3 (GPLv3)
Classifier: Operating System :: OS Independent
Classifier: Development Status :: 3 - Alpha
Classifier: Intended Audience :: Developers
Classifier: Topic :: Utilities
Requires-Python: >=3.6
License-File: LICENSE
Requires-Dist: requests
Requires-Dist: openai
